[
  // Please keep sorted by Name.
  {
    "Name": "Allow Modded Achievements",
    "Author": "AlterAsc",
    "Id": {
      "Id": "AllowModdedAchievements",
      "Type": "UMM"
    },
    "Service": {
      "Github": {
        "Owner": "alterasc",
        "RepoName": "RT_AllowModdedAchievements"
      }
    },
    "About": "Separate mod to allow achievements while modded.",
    "HomepageUrl": "https://www.nexusmods.com/warhammer40kroguetrader/mods/4",
    "Tags": [ "Gameplay", "Utilities" ]
  },

  {
    "Name": "Enhanced Controls",
    "Author": "AlterAsc",
    "Id": {
      "Id": "EnhancedControls",
      "Type": "UMM"
    },
    "Service": {
      "Nexus": {
        "Owner": "14"
      }
    },
    "About": "Adds couple of new keybindings",
    "HomepageUrl": "https://www.nexusmods.com/warhammer40kroguetrader/mods/14",
    "Tags": [ "Gameplay", "Utilities" ]
  },

  {
    "Name": "Skill Check Assistant",
    "Author": "AlterAsc",
    "Id": {
      "Id": "SkillCheckAssistant",
      "Type": "UMM"
    },
    "Service": {
      "Github": {
        "Owner": "alterasc",
        "RepoName": "SkillCheckAssistant"
      }
    },
    "About": "Allows taking (rolling preset value) when doing skill checks. Available options are: roll normally, take 50, take 33, take 25, take 10, take 1. Settings are per individual skill.",
    "HomepageUrl": "https://www.nexusmods.com/warhammer40kroguetrader/mods/3",
    "Tags": [ "Gameplay", "Utilities" ]
  },

  {
    "Name": "ToyBox (a bag of tricks)",
    "Author": "Narria",
    "Id": {
      "Id": "0ToyBox0",
      "Type": "UMM"
    },
    "Service": {
      "Github": {
        "Owner": "xADDBx",
        "RepoName": "ToyBox"
      }
    },
    "About": "Toy Box is a cute and playful mod with 400+ cheats, tweaks and quality of life improvements. It was created in the spirit of Bag of Tricks & Cheat Menu but with a little different focus.",
    "HomepageUrl": "https://www.nexusmods.com/warhammer40kroguetrader/mods/1",
    "Tags": [ "Gameplay", "Utilities" ]
  }

]